{
  "project_info": {
    "project_number": "657539785527",
    "project_id": "trudyagi-cfe25",
    "storage_bucket": "trudyagi-cfe25.appspot.com"
  },
  "client": [
    {
      "client_info": {
        "mobilesdk_app_id": "1:657539785527:android:833d708adab65d2f1c30b2",
        "android_client_info": {
          "package_name": "com.trudyagiRF.trudyagi"
        }
      },
      "oauth_client": [
        {
          "client_id": "657539785527-ctco7je72g6olt0b38rdbq5sli5ueror.apps.googleusercontent.com",
          "client_type": 3
        }
      ],
      "api_key": [
        {
          "current_key": "AIzaSyDyCgbmhbygN2vPuNaLgWtcb2iVwd0oAkA"
        }
      ],
      "services": {
        "appinvite_service": {
          "other_platform_oauth_client": [
            {
              "client_id": "657539785527-ctco7je72g6olt0b38rdbq5sli5ueror.apps.googleusercontent.com",
              "client_type": 3
            }
          ]
        }
      }
    }
  ],
  "configuration_version": "1"
}